ga_storage_manager/__init__.py
ga_storage_manager/exceptions.py
ga_storage_manager-1.0.3.dist-info/METADATA
ga_storage_manager-1.0.3.dist-info/RECORD
ga_storage_manager-1.0.3.dist-info/WHEEL
ga_storage_manager-1.0.3.dist-info/top_level.txt
