Metadata-Version: 2.1
Name: ga-storage-manager
Version: 1.0.3
Summary: This is a (POC) simple json storage manager.
Home-page: https://github.com/geraldoandradee/ga-storage-manager
Author: Geraldo Andrade
Author-email: geraldo@geraldoandrade.com
License: MIT
Platform: UNKNOWN
Classifier: Programming Language :: Python :: 2
Classifier: Programming Language :: Python :: 3
Classifier: License :: OSI Approved :: MIT License
Classifier: Operating System :: OS Independent
